pconv_lib/__init__.py
pconv_lib/pconv.py
pconv_lib-0.0.3.dist-info/LICENSE
pconv_lib-0.0.3.dist-info/METADATA
pconv_lib-0.0.3.dist-info/WHEEL
pconv_lib-0.0.3.dist-info/top_level.txt
pconv_lib-0.0.3.dist-info/RECORD
