Metadata-Version: 2.1
Name: pconv-lib
Version: 0.0.3
Summary: Convert Python Data to JS through JSON
Author: Jaival Patel
License: MIT License        
Project-URL: Homepage, https://github.com/GEEGABYTE1/pconv
Project-URL: Bug Tracker, https://github.com/GEEGABYTE1/pconv/issues
Classifier: Programming Language :: Python :: 3
Classifier: License :: OSI Approved :: MIT License
Classifier: Operating System :: OS Independent
Requires-Python: >=3.7
License-File: LICENSE
